emerald_hws/__init__.py
emerald_hws/emeraldhws.py
emerald_hws/__assets__/SFSRootCAG2.pem
emerald_hws-0.0.25.dist-info/METADATA
emerald_hws-0.0.25.dist-info/WHEEL
emerald_hws-0.0.25.dist-info/top_level.txt
emerald_hws-0.0.25.dist-info/RECORD
