Metadata-Version: 2.4
Name: emerald_hws
Version: 0.0.25
Summary: A package to manipulate and monitor Emerald Heat Pump Hot Water Systems
Author-email: Ross Williamson <ross@inertia.net.nz>
License-Expression: MIT
Project-URL: Homepage, https://github.com/ross-w/emerald_hws_py
Project-URL: Bug Tracker, https://github.com/ross-w/emerald_hws_py/issues
Classifier: Programming Language :: Python :: 3
Classifier: Operating System :: OS Independent
Requires-Python: >=3.9
Requires-Dist: boto3<2.0.0,>=1.40.0
Requires-Dist: awsiotsdk<2.0.0,>=1.24.0
Requires-Dist: requests>=2.25.0
Provides-Extra: dev
Requires-Dist: ruff<1.0.0,>=0.12.0; extra == "dev"
Requires-Dist: pre-commit>=3.0.0; extra == "dev"
Provides-Extra: test
Requires-Dist: pytest>=7.0.0; extra == "test"
Requires-Dist: pytest-cov>=4.0.0; extra == "test"
Requires-Dist: pytest-asyncio>=0.21.0; extra == "test"
Requires-Dist: pytest-mock>=3.10.0; extra == "test"
